rotating_calipers/__init__.py
rotating_calipers/convexhull.py
rotating_calipers/geometry.py
rotating_calipers/rotating_calipers.py
rotating_calipers-1.0.dist-info/METADATA
rotating_calipers-1.0.dist-info/WHEEL
rotating_calipers-1.0.dist-info/top_level.txt
rotating_calipers-1.0.dist-info/RECORD
