Metadata-Version: 2.1
Name: rotating_calipers
Version: 1.0
Summary: UNKNOWN
Home-page: UNKNOWN
License: UNKNOWN
Platform: UNKNOWN
